AutoDiffpy/AutoDiffpy.py
AutoDiffpy/ElementaryFunc.py
AutoDiffpy/Node.py
AutoDiffpy/__init__.py
AutoDiffpy/dual.py
AutoDiffpy/setup.py
Testpy/__init__.py
Testpy/test.py
AutoDiffpyy-1.0.dist-info/LICENSE
AutoDiffpyy-1.0.dist-info/METADATA
AutoDiffpyy-1.0.dist-info/WHEEL
AutoDiffpyy-1.0.dist-info/top_level.txt
AutoDiffpyy-1.0.dist-info/RECORD
